join_logninja_docker_swarm/__init__.py
join_logninja_docker_swarm/setup_node.py
logninja_join_swarm-0.1.1.dev0.dist-info/licenses/LICENSE
logninja_join_swarm-0.1.1.dev0.dist-info/METADATA
logninja_join_swarm-0.1.1.dev0.dist-info/WHEEL
logninja_join_swarm-0.1.1.dev0.dist-info/entry_points.txt
logninja_join_swarm-0.1.1.dev0.dist-info/top_level.txt
logninja_join_swarm-0.1.1.dev0.dist-info/RECORD
