Metadata-Version: 2.4
Name: logninja-join-swarm
Version: 0.1.1.dev0
Summary: Auto-join a machine to the LogNinja Docker Swarm cluster
Author: Nathan
Keywords: docker,swarm,logninja,setup,ai
Classifier: Programming Language :: Python :: 3
Classifier: Operating System :: POSIX :: Linux
License-File: LICENSE
Dynamic: author
Dynamic: classifier
Dynamic: keywords
Dynamic: license-file
Dynamic: summary
